trajectorydata/__init__.py
trajectorydata-0.1.0.dist-info/DESCRIPTION.rst
trajectorydata-0.1.0.dist-info/METADATA
trajectorydata-0.1.0.dist-info/RECORD
trajectorydata-0.1.0.dist-info/WHEEL
trajectorydata-0.1.0.dist-info/metadata.json
trajectorydata-0.1.0.dist-info/top_level.txt
