Metadata-Version: 2.0
Name: trajectorydata
Version: 0.1.0
Summary: Package providing the TrajectoryData class that allows to manage data for observables from a large number of quantum trajectory simulations
Home-page: https://github.com/goerz/trajectorydata
Author: Michael Goerz
Author-email: mail@michaelgoerz.net
License: MIT license
Keywords: trajectorydata
Platform: UNKNOWN
Classifier: Development Status :: 2 - Pre-Alpha
Classifier: Intended Audience :: Developers
Classifier: License :: OSI Approved :: MIT License
Classifier: Natural Language :: English
Classifier: Programming Language :: Python :: 3.5
Classifier: Programming Language :: Python :: 3.6
Provides-Extra: dev
Provides-Extra: dev
Requires-Dist: coverage; extra == 'dev'
Requires-Dist: pytest; extra == 'dev'
Requires-Dist: pytest-cov; extra == 'dev'
Requires-Dist: pytest-xdist; extra == 'dev'
Requires-Dist: twine; extra == 'dev'
Requires-Dist: pep8; extra == 'dev'
Requires-Dist: flake8; extra == 'dev'
Requires-Dist: wheel; extra == 'dev'
Requires-Dist: sphinx; extra == 'dev'
Requires-Dist: sphinx-autobuild; extra == 'dev'
Requires-Dist: sphinx-rtd-theme; extra == 'dev'
Requires-Dist: better-apidoc; extra == 'dev'
